LICENCE.txt
README.md
setup.py
neten/__init__.py
neten.egg-info/PKG-INFO
neten.egg-info/SOURCES.txt
neten.egg-info/dependency_links.txt
neten.egg-info/requires.txt
neten.egg-info/top_level.txt